waco/__init__.py
waco/analyzer.py
waco/sim.py
waco-0.1.0.dist-info/LICENSE
waco-0.1.0.dist-info/METADATA
waco-0.1.0.dist-info/WHEEL
waco-0.1.0.dist-info/top_level.txt
waco-0.1.0.dist-info/RECORD
