Metadata-Version: 2.1
Name: waco
Version: 0.1.0
Summary: Simulate the diffusion of contaminants in water networks.
Home-page: https://andreaponti5.github.io/waco
Author: Andrea Ponti
Author-email: ponti.andrea97@gmail.com
License: MIT
Project-URL: Documentation, https://andreaponti5.github.io/waco
Project-URL: Source, https://github.com/andreaponti5/waco
Classifier: Intended Audience :: Developers
Classifier: License :: OSI Approved :: MIT License
Classifier: Programming Language :: Python
Classifier: Operating System :: OS Independent
License-File: LICENSE
Requires-Dist: wntr
